pricehubble_api/__config__.py
pricehubble_api/__init__.py
pricehubble_api/__main__.py
pricehubble_api/_version.py
pricehubble_api/exceptions.py
pricehubble_api/models.py
pricehubble_api/_tests/__init__.py
pricehubble_api/_tests/test_dummy.py
pricehubble_api-0.0.3.dist-info/LICENSE
pricehubble_api-0.0.3.dist-info/METADATA
pricehubble_api-0.0.3.dist-info/WHEEL
pricehubble_api-0.0.3.dist-info/top_level.txt
pricehubble_api-0.0.3.dist-info/RECORD
